easyoanda/__init__.py
easyoanda/easyoanda.py
easyoanda/modules/comms.py
easyoanda/modules/monitor.py
easyoanda/modules/prebuild.py
easyoanda/modules/session.py
easyoanda-1.0.19.dist-info/METADATA
easyoanda-1.0.19.dist-info/WHEEL
easyoanda-1.0.19.dist-info/licenses/LICENSE
easyoanda-1.0.19.dist-info/RECORD
