Metadata-Version: 2.3
Name: easyoanda
Version: 1.0.19
Summary: #easyoanda - an easier way to trade your OANDA account.
Author-email: Karsten Cadley <ktcdevworks@gmail.com>
License-File: LICENSE
Keywords: FX,currency,finance,foreign exchange,forex,investing,oanda,trading,trading API
Classifier: Development Status :: 3 - Alpha
Classifier: Intended Audience :: Developers
Classifier: License :: OSI Approved :: Apache Software License
Classifier: Operating System :: OS Independent
Classifier: Programming Language :: Python :: 3.11
Classifier: Programming Language :: Python :: 3.12
Classifier: Topic :: Education
Classifier: Topic :: Office/Business :: Financial
Classifier: Topic :: Office/Business :: Financial :: Accounting
Classifier: Topic :: Office/Business :: Financial :: Investment
Classifier: Topic :: Software Development :: Libraries
Classifier: Topic :: Software Development :: Libraries :: Python Modules
Requires-Python: >=3.11
Requires-Dist: pandas>=1.5.3
Requires-Dist: requests>=2.28.1
